prometheus_mcp_server/__init__.py
prometheus_mcp_server/__main__.py
prometheus_mcp_server/cli.py
prometheus_mcp_server/server.py
prometheus_mcp_server/tools/__init__.py
prometheus_mcp_server/tools/registry.py
prometheus_mcp_server/utils/__init__.py
prometheus_mcp_server/utils/client.py
prometheus_mcp_server/utils/helpers.py
msrashed_prometheus_mcp_server-0.2.2.dist-info/METADATA
msrashed_prometheus_mcp_server-0.2.2.dist-info/WHEEL
msrashed_prometheus_mcp_server-0.2.2.dist-info/entry_points.txt
msrashed_prometheus_mcp_server-0.2.2.dist-info/licenses/LICENSE
msrashed_prometheus_mcp_server-0.2.2.dist-info/RECORD
